pdfgpt/__init__.py
pdfgpt/cli.py
pdfgpt/pdfgpt.py
pdfgpt-0.1.0.dist-info/LICENSE
pdfgpt-0.1.0.dist-info/METADATA
pdfgpt-0.1.0.dist-info/WHEEL
pdfgpt-0.1.0.dist-info/entry_points.txt
pdfgpt-0.1.0.dist-info/top_level.txt
pdfgpt-0.1.0.dist-info/RECORD
