Metadata-Version: 2.1
Name: pdfgpt
Version: 0.1.0
Summary: pdfgpt is a Python package that provides users with the ability to engage in natural language conversations with their PDF documents.
Home-page: https://github.com/Mariosmsk/pdfgpt
Author: Marios S. Kyriakou
Author-email: kiriakou.marios@ucy.ac.cy
License: MIT license
Keywords: pdfgpt
Classifier: Development Status :: 2 - Pre-Alpha
Classifier: Intended Audience :: Developers
Classifier: License :: OSI Approved :: MIT License
Classifier: Natural Language :: English
Classifier: Programming Language :: Python :: 3
Classifier: Programming Language :: Python :: 3.6
Classifier: Programming Language :: Python :: 3.7
Classifier: Programming Language :: Python :: 3.8
Requires-Python: >=3.6
License-File: LICENSE
Requires-Dist: Click (>=7.0)
Requires-Dist: openai
Requires-Dist: pandas
Requires-Dist: pypdf
